sand/__init__.py
sand/__main__.py
sand/app.py
sand/client.py
sand/commands/__init__.py
sand/commands/load.py
sand/config.py
sand/controllers/__init__.py
sand/controllers/assistant.py
sand/controllers/helpers/__init__.py
sand/controllers/helpers/upload.py
sand/controllers/project.py
sand/controllers/settings.py
sand/controllers/table.py
sand/deserializer.py
sand/models/__init__.py
sand/models/base.py
sand/models/entity.py
sand/models/ontology.py
sand/models/project.py
sand/models/semantic_model.py
sand/models/table.py
sand/models/uploading_table.py.deprecated
sand/plugins/__init__.py
sand/plugins/drepr/__init__.py
sand/plugins/drepr/raw_transformations/global_coordinate.py
sand/plugins/drepr/raw_transformations/number.py
sand/plugins/drepr/relational2rdf.py
sand/plugins/drepr/resources.py
sand/plugins/drepr/semanticmodel.py
sand/plugins/drepr/transformation.py
sand/plugins/grams_plugin.py
sand/plugins/mtab.py
sand/plugins/wikidata.py
sand/serializer.py
sand/www/asset-manifest.json
sand/www/favicon.ico
sand/www/index.html
sand/www/logo192.png
sand/www/logo512.png
sand/www/manifest.json
sand/www/robots.txt
sand/www/static/css/2.b3380b9b.chunk.css
sand/www/static/css/2.b3380b9b.chunk.css.map
sand/www/static/css/main.8470bb9a.chunk.css
sand/www/static/css/main.8470bb9a.chunk.css.map
sand/www/static/js/2.86cb8b5b.chunk.js
sand/www/static/js/2.86cb8b5b.chunk.js.LICENSE.txt
sand/www/static/js/2.86cb8b5b.chunk.js.map
sand/www/static/js/3.28cb8f3e.chunk.js
sand/www/static/js/3.28cb8f3e.chunk.js.map
sand/www/static/js/main.ec118bae.chunk.js
sand/www/static/js/main.ec118bae.chunk.js.map
sand/www/static/js/runtime-main.3b0ba70d.js
sand/www/static/js/runtime-main.3b0ba70d.js.map
sand/www/static/media/default.003f90b3.less
sand/www/static/media/index.00515a28.less
sand/www/static/media/index.055e5992.less
sand/www/static/media/index.0b3b5180.less
sand/www/static/media/index.222b2c74.less
sand/www/static/media/index.24d39731.less
sand/www/static/media/index.3f817bd9.less
sand_py-2.1.9.dev0.dist-info/entry_points.txt
sand_py-2.1.9.dev0.dist-info/WHEEL
sand_py-2.1.9.dev0.dist-info/METADATA
sand_py-2.1.9.dev0.dist-info/RECORD
