Metadata-Version: 2.1
Name: sand.py
Version: 2.1.9.dev0
Summary: UI for browsing/editing semantic descriptions
Home-page: https://github.com/usc-isi-i2/sand
License: MIT
Author: Binh Vu
Author-email: binh@toan2.com
Requires-Python: >=3.8,<3.11
Classifier: License :: OSI Approved :: MIT License
Classifier: Programming Language :: Python :: 3
Classifier: Programming Language :: Python :: 3.8
Classifier: Programming Language :: Python :: 3.9
Classifier: Programming Language :: Python :: 3.10
Requires-Dist: Flask (>=2.0.2,<3.0.0)
Requires-Dist: drepr (>=2.10.0,<3.0.0)
Requires-Dist: gena (>=1.1.2,<2.0.0)
Requires-Dist: kgdata (>=3.0.2,<4.0.0)
Requires-Dist: lat_lon_parser (>=1.3.0,<2.0.0)
Requires-Dist: loguru (>=0.6.0)
Requires-Dist: orjson (>=3.6.8,<4.0.0)
Requires-Dist: peewee (>=3.14.4,<4.0.0)
Requires-Dist: python-dotenv (>=0.19.0)
Requires-Dist: sem-desc (>=3.5.2,<4.0.0)
Requires-Dist: sm-grams (>=2.1.3,<3.0.0)
Requires-Dist: tornado (>=6.1,<7.0)
Project-URL: Repository, https://github.com/usc-isi-i2/sand
